{
  "$schema": "https://developer.microsoft.com/json-schemas/fabric/item/report/definition/visualContainer/2.4.0/schema.json",
  "name": "390209dd75808ed566a8",
  "position": {
    "x": 641.538461538461,
    "y": 352.30769230769232,
    "z": 11000,
    "height": 254.61538461538461,
    "width": 486.15384615384613,
    "tabOrder": 9000
  },
  "visual": {
    "visualType": "clusteredColumnChart",
    "query": {
      "queryState": {
        "Category": {
          "projections": [
            {
              "field": {
                "Column": {
                  "Expression": {
                    "SourceRef": {
                      "Entity": "Dim_farmers"
                    }
                  },
                  "Property": "farmer_gender"
                }
              },
              "queryRef": "Dim_farmers.farmer_gender",
              "nativeQueryRef": "farmer_gender",
              "active": true
            }
          ]
        },
        "Series": {
          "projections": [
            {
              "field": {
                "Column": {
                  "Expression": {
                    "SourceRef": {
                      "Entity": "Dim_subprojectwaves"
                    }
                  },
                  "Property": "subproject_wave"
                }
              },
              "queryRef": "Dim_subprojectwaves.subproject_wave",
              "nativeQueryRef": "subproject_wave"
            }
          ]
        },
        "Y": {
          "projections": [
            {
              "field": {
                "Measure": {
                  "Expression": {
                    "SourceRef": {
                      "Entity": "_Measures_global"
                    }
                  },
                  "Property": "producers at planting registry"
                }
              },
              "queryRef": "_Measures_global.producers at planting registry",
              "nativeQueryRef": "producers at planting registry"
            }
          ]
        }
      },
      "sortDefinition": {
        "sort": [
          {
            "field": {
              "Measure": {
                "Expression": {
                  "SourceRef": {
                    "Entity": "_Measures_global"
                  }
                },
                "Property": "producers at planting registry"
              }
            },
            "direction": "Descending"
          },
          {
            "field": {
              "Column": {
                "Expression": {
                  "SourceRef": {
                    "Entity": "Dim_subprojectwaves"
                  }
                },
                "Property": "subproject_wave"
              }
            },
            "direction": "Descending"
          }
        ]
      }
    },
    "objects": {
      "general": [
        {
          "properties": {}
        }
      ],
      "legend": [
        {
          "properties": {
            "position": {
              "expr": {
                "Literal": {
                  "Value": "'BottomCenter'"
                }
              }
            },
            "showTitle": {
              "expr": {
                "Literal": {
                  "Value": "false"
                }
              }
            },
            "fontFamily": {
              "expr": {
                "Literal": {
                  "Value": "'Arial'"
                }
              }
            }
          }
        }
      ],
      "categoryAxis": [
        {
          "properties": {
            "showAxisTitle": {
              "expr": {
                "Literal": {
                  "Value": "false"
                }
              }
            },
            "fontFamily": {
              "expr": {
                "Literal": {
                  "Value": "'Arial'"
                }
              }
            }
          }
        }
      ],
      "valueAxis": [
        {
          "properties": {
            "gridlineShow": {
              "expr": {
                "Literal": {
                  "Value": "false"
                }
              }
            },
            "end": {
              "expr": {
                "Literal": {
                  "Value": "436D"
                }
              }
            },
            "start": {
              "expr": {
                "Literal": {
                  "Value": "0.8D"
                }
              }
            },
            "invertAxis": {
              "expr": {
                "Literal": {
                  "Value": "false"
                }
              }
            },
            "logAxisScale": {
              "expr": {
                "Literal": {
                  "Value": "true"
                }
              }
            },
            "showAxisTitle": {
              "expr": {
                "Literal": {
                  "Value": "false"
                }
              }
            },
            "show": {
              "expr": {
                "Literal": {
                  "Value": "false"
                }
              }
            },
            "labelPrecision": {
              "expr": {
                "Literal": {
                  "Value": "0L"
                }
              }
            }
          }
        }
      ],
      "dataPoint": [
        {
          "properties": {
            "fill": {
              "solid": {
                "color": {
                  "expr": {
                    "Literal": {
                      "Value": "'#9A4241'"
                    }
                  }
                }
              }
            }
          },
          "selector": {
            "data": [
              {
                "scopeId": {
                  "Comparison": {
                    "ComparisonKind": 0,
                    "Left": {
                      "Column": {
                        "Expression": {
                          "SourceRef": {
                            "Entity": "Dim_subprojectwaves"
                          }
                        },
                        "Property": "subproject_wave"
                      }
                    },
                    "Right": {
                      "Literal": {
                        "Value": "'acopagro-w24'"
                      }
                    }
                  }
                }
              }
            ]
          }
        },
        {
          "properties": {
            "fill": {
              "solid": {
                "color": {
                  "expr": {
                    "Literal": {
                      "Value": "'#809177'"
                    }
                  }
                }
              }
            }
          },
          "selector": {
            "data": [
              {
                "scopeId": {
                  "Comparison": {
                    "ComparisonKind": 0,
                    "Left": {
                      "Column": {
                        "Expression": {
                          "SourceRef": {
                            "Entity": "Dim_subprojectwaves"
                          }
                        },
                        "Property": "subproject_wave"
                      }
                    },
                    "Right": {
                      "Literal": {
                        "Value": "'oro verde-w24'"
                      }
                    }
                  }
                }
              }
            ]
          }
        }
      ],
      "labels": [
        {
          "properties": {
            "show": {
              "expr": {
                "Literal": {
                  "Value": "true"
                }
              }
            },
            "labelPosition": {
              "expr": {
                "Literal": {
                  "Value": "'Auto'"
                }
              }
            },
            "enableTitleDataLabel": {
              "expr": {
                "Literal": {
                  "Value": "false"
                }
              }
            }
          }
        }
      ]
    },
    "visualContainerObjects": {
      "title": [
        {
          "properties": {
            "text": {
              "expr": {
                "Literal": {
                  "Value": "'Participants Enrroled (at Planting Registry'"
                }
              }
            },
            "show": {
              "expr": {
                "Literal": {
                  "Value": "true"
                }
              }
            },
            "titleWrap": {
              "expr": {
                "Literal": {
                  "Value": "true"
                }
              }
            },
            "fontColor": {
              "solid": {
                "color": {
                  "expr": {
                    "ThemeDataColor": {
                      "ColorId": 0,
                      "Percent": -0.6
                    }
                  }
                }
              }
            },
            "fontSize": {
              "expr": {
                "Literal": {
                  "Value": "11D"
                }
              }
            },
            "bold": {
              "expr": {
                "Literal": {
                  "Value": "true"
                }
              }
            },
            "fontFamily": {
              "expr": {
                "Literal": {
                  "Value": "'Arial'"
                }
              }
            }
          }
        }
      ],
      "subTitle": [
        {
          "properties": {
            "show": {
              "expr": {
                "Literal": {
                  "Value": "false"
                }
              }
            },
            "fontFamily": {
              "expr": {
                "Literal": {
                  "Value": "'Inter'"
                }
              }
            }
          }
        }
      ],
      "divider": [
        {
          "properties": {
            "show": {
              "expr": {
                "Literal": {
                  "Value": "false"
                }
              }
            }
          }
        }
      ],
      "background": [
        {
          "properties": {
            "show": {
              "expr": {
                "Literal": {
                  "Value": "true"
                }
              }
            },
            "transparency": {
              "expr": {
                "Literal": {
                  "Value": "0D"
                }
              }
            }
          }
        }
      ],
      "padding": [
        {
          "properties": {
            "bottom": {
              "expr": {
                "Literal": {
                  "Value": "5D"
                }
              }
            },
            "left": {
              "expr": {
                "Literal": {
                  "Value": "5D"
                }
              }
            }
          }
        }
      ],
      "lockAspect": [
        {
          "properties": {
            "show": {
              "expr": {
                "Literal": {
                  "Value": "false"
                }
              }
            }
          }
        }
      ],
      "border": [
        {
          "properties": {
            "show": {
              "expr": {
                "Literal": {
                  "Value": "true"
                }
              }
            },
            "color": {
              "solid": {
                "color": {
                  "expr": {
                    "ThemeDataColor": {
                      "ColorId": 0,
                      "Percent": 0
                    }
                  }
                }
              }
            },
            "radius": {
              "expr": {
                "Literal": {
                  "Value": "3D"
                }
              }
            },
            "width": {
              "expr": {
                "Literal": {
                  "Value": "1D"
                }
              }
            }
          }
        }
      ],
      "dropShadow": [
        {
          "properties": {
            "show": {
              "expr": {
                "Literal": {
                  "Value": "true"
                }
              }
            },
            "color": {
              "solid": {
                "color": {
                  "expr": {
                    "ThemeDataColor": {
                      "ColorId": 0,
                      "Percent": -0.5
                    }
                  }
                }
              }
            }
          }
        }
      ],
      "visualTooltip": [
        {
          "properties": {
            "fontFamily": {
              "expr": {
                "Literal": {
                  "Value": "'Inter'"
                }
              }
            }
          }
        }
      ],
      "visualHeaderTooltip": [
        {
          "properties": {
            "fontFamily": {
              "expr": {
                "Literal": {
                  "Value": "'Inter'"
                }
              }
            }
          }
        }
      ]
    },
    "drillFilterOtherVisuals": true
  },
  "filterConfig": {
    "filters": [
      {
        "name": "e2a2b34770d947e381e9",
        "field": {
          "Column": {
            "Expression": {
              "SourceRef": {
                "Entity": "Dim_farmers"
              }
            },
            "Property": "farmer_gender"
          }
        },
        "type": "Categorical"
      },
      {
        "name": "56f1154670c3dcb40d3d",
        "field": {
          "Column": {
            "Expression": {
              "SourceRef": {
                "Entity": "Dim_subprojectwaves"
              }
            },
            "Property": "subproject_wave"
          }
        },
        "type": "Categorical"
      },
      {
        "name": "33a64b7037b0cd279027",
        "field": {
          "Measure": {
            "Expression": {
              "SourceRef": {
                "Entity": "_Measures_global"
              }
            },
            "Property": "producers at planting registry"
          }
        },
        "type": "Advanced"
      }
    ]
  }
}